crispy_forms_uikit/__init__.py
crispy_forms_uikit/layout/__init__.py
crispy_forms_uikit/layout/base.py
crispy_forms_uikit/layout/buttons.py
crispy_forms_uikit/layout/fields.py
crispy_forms_uikit/layout/grid.py
crispy_forms_uikit/settings.py
crispy_forms_uikit/templates/uikit-3.4.0/display_form.html
crispy_forms_uikit/templates/uikit-3.4.0/errors.html
crispy_forms_uikit/templates/uikit-3.4.0/field.html
crispy_forms_uikit/templates/uikit-3.4.0/layout/__init__.py
crispy_forms_uikit/templates/uikit-3.4.0/layout/base.py
crispy_forms_uikit/templates/uikit-3.4.0/layout/basebutton.html
crispy_forms_uikit/templates/uikit-3.4.0/layout/baseinput.html
crispy_forms_uikit/templates/uikit-3.4.0/layout/buttongroup.html
crispy_forms_uikit/templates/uikit-3.4.0/layout/checkboxselectmultiple.html
crispy_forms_uikit/templates/uikit-3.4.0/layout/div.html
crispy_forms_uikit/templates/uikit-3.4.0/layout/empty.html
crispy_forms_uikit/templates/uikit-3.4.0/layout/fieldset.html
crispy_forms_uikit/templates/uikit-3.4.0/layout/input.py
crispy_forms_uikit/templates/uikit-3.4.0/uni_form.html
crispy_forms_uikit/templates/uikit-3.4.0/whole_uni_form.html
crispy_forms_uikit/templatetags/__init__.py
crispy_forms_uikit/templatetags/crispy_forms_uikit.py
crispy_forms_uikit/whole_uni_form.html.py
crispy_forms_uikit-0.2.0.dist-info/LICENSE.txt
crispy_forms_uikit-0.2.0.dist-info/WHEEL
crispy_forms_uikit-0.2.0.dist-info/METADATA
crispy_forms_uikit-0.2.0.dist-info/RECORD
