Metadata-Version: 2.1
Name: crispy-forms-uikit
Version: 0.2.0
Summary: 
License: MIT
Author: Jan Willems
Author-email: jw@elevenbts.com
Requires-Python: >=3.8,<4.0
Classifier: License :: OSI Approved :: MIT License
Classifier: Programming Language :: Python :: 3
Classifier: Programming Language :: Python :: 3.8
Requires-Dist: Django (>=2.1)
Requires-Dist: django-crispy-forms (>=1.9.0,<2.0.0)
